{"rc":3185, "rcc":"0504013", "rn":"ILAWOD", "can":"Barangay", "cll":true, "cl":5, "url":"3/3185", "srs":{}, "tcs":[], "cs":[1, 87, 701, 6, 394, 3968, 5567, 174, 2335], "pps":[{"ppc":2396, "ppcc":"05040018", "ppn":"GUINOBATAN WEST CENTRAL SCHOOL", "vbs":[{"vbc":2396, "pre":"05040018", "cpre":"0042A, 0043A, 0044A, 0045A, 0046A", "url":"2/2396", "type":"AUTOMATED", "cs":[1, 6, 87, 174, 394, 701, 2335, 3968, 5567]}]}, {"ppc":2397, "ppcc":"05040019", "ppn":"GUINOBATAN WEST CENTRAL SCHOOL", "vbs":[{"vbc":2397, "pre":"05040019", "cpre":"0047A, 0048A, 0048B, 0049A", "url":"2/2397", "type":"AUTOMATED", "cs":[1, 6, 87, 174, 394, 701, 2335, 3968, 5567]}]}], "total-vb":2, "total-voters":1543}