{"vbc":26616, "rs":[{"cc":1, "bo":1, "v":6, "tot":5332, "per":"0.11", "ser":"HPM180PA01006615"}, {"cc":1, "bo":2, "v":9, "tot":5332, "per":"0.16", "ser":"HPM180PA01006615"}, {"cc":1, "bo":3, "v":55, "tot":5332, "per":"1.03", "ser":"HPM180PA01006615"}, {"cc":1, "bo":4, "v":1, "tot":5332, "per":"0.01", "ser":"HPM180PA01006615"}, {"cc":1, "bo":5, "v":10, "tot":5332, "per":"0.18", "ser":"HPM180PA01006615"}, {"cc":1, "bo":6, "v":2, "tot":5332, "per":"0.03", "ser":"HPM180PA01006615"}, {"cc":1, "bo":7, "v":48, "tot":5332, "per":"0.90", "ser":"HPM180PA01006615"}, {"cc":1, "bo":8, "v":334, "tot":5332, "per":"6.26", "ser":"HPM180PA01006615"}, {"cc":1, "bo":9, "v":96, "tot":5332, "per":"1.80", "ser":"HPM180PA01006615"}, {"cc":1, "bo":10, "v":3, "tot":5332, "per":"0.05", "ser":"HPM180PA01006615"}, {"cc":1, "bo":11, "v":4, "tot":5332, "per":"0.07", "ser":"HPM180PA01006615"}, {"cc":1, "bo":12, "v":2, "tot":5332, "per":"0.03", "ser":"HPM180PA01006615"}, {"cc":1, "bo":13, "v":4, "tot":5332, "per":"0.07", "ser":"HPM180PA01006615"}, {"cc":1, "bo":14, "v":2, "tot":5332, "per":"0.03", "ser":"HPM180PA01006615"}, {"cc":1, "bo":15, "v":159, "tot":5332, "per":"2.98", "ser":"HPM180PA01006615"}, {"cc":1, "bo":16, "v":185, "tot":5332, "per":"3.46", "ser":"HPM180PA01006615"}, {"cc":1, "bo":17, "v":1, "tot":5332, "per":"0.01", "ser":"HPM180PA01006615"}, {"cc":1, "bo":18, "v":7, "tot":5332, "per":"0.13", "ser":"HPM180PA01006615"}, {"cc":1, "bo":19, "v":369, "tot":5332, "per":"6.92", "ser":"HPM180PA01006615"}, {"cc":1, "bo":20, "v":8, "tot":5332, "per":"0.15", "ser":"HPM180PA01006615"}, {"cc":1, "bo":21, "v":54, "tot":5332, "per":"1.01", "ser":"HPM180PA01006615"}, {"cc":1, "bo":22, "v":18, "tot":5332, "per":"0.33", "ser":"HPM180PA01006615"}, {"cc":1, "bo":23, "v":5, "tot":5332, "per":"0.09", "ser":"HPM180PA01006615"}, {"cc":1, "bo":24, "v":469, "tot":5332, "per":"8.79", "ser":"HPM180PA01006615"}, {"cc":1, "bo":25, "v":26, "tot":5332, "per":"0.48", "ser":"HPM180PA01006615"}, {"cc":1, "bo":26, "v":278, "tot":5332, "per":"5.21", "ser":"HPM180PA01006615"}, {"cc":1, "bo":27, "v":56, "tot":5332, "per":"1.05", "ser":"HPM180PA01006615"}, {"cc":1, "bo":28, "v":23, "tot":5332, "per":"0.43", "ser":"HPM180PA01006615"}, {"cc":1, "bo":29, "v":145, "tot":5332, "per":"2.71", "ser":"HPM180PA01006615"}, {"cc":1, "bo":30, "v":2, "tot":5332, "per":"0.03", "ser":"HPM180PA01006615"}, {"cc":1, "bo":31, "v":2, "tot":5332, "per":"0.03", "ser":"HPM180PA01006615"}, {"cc":1, "bo":32, "v":60, "tot":5332, "per":"1.12", "ser":"HPM180PA01006615"}, {"cc":1, "bo":33, "v":4, "tot":5332, "per":"0.07", "ser":"HPM180PA01006615"}, {"cc":1, "bo":34, "v":483, "tot":5332, "per":"9.05", "ser":"HPM180PA01006615"}, {"cc":1, "bo":35, "v":6, "tot":5332, "per":"0.11", "ser":"HPM180PA01006615"}, {"cc":1, "bo":36, "v":12, "tot":5332, "per":"0.22", "ser":"HPM180PA01006615"}, {"cc":1, "bo":37, "v":6, "tot":5332, "per":"0.11", "ser":"HPM180PA01006615"}, {"cc":1, "bo":38, "v":3, "tot":5332, "per":"0.05", "ser":"HPM180PA01006615"}, {"cc":1, "bo":39, "v":4, "tot":5332, "per":"0.07", "ser":"HPM180PA01006615"}, {"cc":1, "bo":40, "v":178, "tot":5332, "per":"3.33", "ser":"HPM180PA01006615"}, {"cc":1, "bo":41, "v":11, "tot":5332, "per":"0.20", "ser":"HPM180PA01006615"}, {"cc":1, "bo":42, "v":3, "tot":5332, "per":"0.05", "ser":"HPM180PA01006615"}, {"cc":1, "bo":43, "v":78, "tot":5332, "per":"1.46", "ser":"HPM180PA01006615"}, {"cc":1, "bo":44, "v":258, "tot":5332, "per":"4.83", "ser":"HPM180PA01006615"}, {"cc":1, "bo":45, "v":70, "tot":5332, "per":"1.31", "ser":"HPM180PA01006615"}, {"cc":1, "bo":46, "v":271, "tot":5332, "per":"5.08", "ser":"HPM180PA01006615"}, {"cc":1, "bo":47, "v":3, "tot":5332, "per":"0.05", "ser":"HPM180PA01006615"}, {"cc":1, "bo":48, "v":1, "tot":5332, "per":"0.01", "ser":"HPM180PA01006615"}, {"cc":1, "bo":49, "v":8, "tot":5332, "per":"0.15", "ser":"HPM180PA01006615"}, {"cc":1, "bo":50, "v":0, "tot":5332, "per":"0.00", "ser":"HPM180PA01006615"}, {"cc":1, "bo":51, "v":84, "tot":5332, "per":"1.57", "ser":"HPM180PA01006615"}, {"cc":1, "bo":52, "v":92, "tot":5332, "per":"1.72", "ser":"HPM180PA01006615"}, {"cc":1, "bo":53, "v":13, "tot":5332, "per":"0.24", "ser":"HPM180PA01006615"}, {"cc":1, "bo":54, "v":285, "tot":5332, "per":"5.34", "ser":"HPM180PA01006615"}, {"cc":1, "bo":55, "v":243, "tot":5332, "per":"4.55", "ser":"HPM180PA01006615"}, {"cc":1, "bo":56, "v":2, "tot":5332, "per":"0.03", "ser":"HPM180PA01006615"}, {"cc":1, "bo":57, "v":36, "tot":5332, "per":"0.67", "ser":"HPM180PA01006615"}, {"cc":1, "bo":58, "v":4, "tot":5332, "per":"0.07", "ser":"HPM180PA01006615"}, {"cc":1, "bo":59, "v":12, "tot":5332, "per":"0.22", "ser":"HPM180PA01006615"}, {"cc":1, "bo":60, "v":319, "tot":5332, "per":"5.98", "ser":"HPM180PA01006615"}, {"cc":1, "bo":61, "v":3, "tot":5332, "per":"0.05", "ser":"HPM180PA01006615"}, {"cc":1, "bo":62, "v":397, "tot":5332, "per":"7.44", "ser":"HPM180PA01006615"}, {"cc":26, "bo":152, "v":410, "tot":410, "per":"100.00", "ser":"HPM180PA01006615"}, {"cc":107, "bo":393, "v":445, "tot":445, "per":"100.00", "ser":"HPM180PA01006615"}, {"cc":238, "bo":1034, "v":239, "tot":1928, "per":"12.39", "ser":"HPM180PA01006615"}, {"cc":238, "bo":1035, "v":237, "tot":1928, "per":"12.29", "ser":"HPM180PA01006615"}, {"cc":238, "bo":1036, "v":88, "tot":1928, "per":"4.56", "ser":"HPM180PA01006615"}, {"cc":238, "bo":1037, "v":224, "tot":1928, "per":"11.61", "ser":"HPM180PA01006615"}, {"cc":238, "bo":1038, "v":207, "tot":1928, "per":"10.73", "ser":"HPM180PA01006615"}, {"cc":238, "bo":1039, "v":13, "tot":1928, "per":"0.67", "ser":"HPM180PA01006615"}, {"cc":238, "bo":1040, "v":287, "tot":1928, "per":"14.88", "ser":"HPM180PA01006615"}, {"cc":238, "bo":1041, "v":410, "tot":1928, "per":"21.26", "ser":"HPM180PA01006615"}, {"cc":238, "bo":1042, "v":223, "tot":1928, "per":"11.56", "ser":"HPM180PA01006615"}, {"cc":459, "bo":2441, "v":464, "tot":464, "per":"100.00", "ser":"HPM180PA01006615"}, {"cc":1124, "bo":4074, "v":286, "tot":657, "per":"43.53", "ser":"HPM180PA01006615"}, {"cc":1124, "bo":4075, "v":371, "tot":657, "per":"56.46", "ser":"HPM180PA01006615"}, {"cc":2758, "bo":7939, "v":325, "tot":636, "per":"51.10", "ser":"HPM180PA01006615"}, {"cc":2758, "bo":7940, "v":311, "tot":636, "per":"48.89", "ser":"HPM180PA01006615"}, {"cc":4398, "bo":20178, "v":50, "tot":4230, "per":"1.18", "ser":"HPM180PA01006615"}, {"cc":4398, "bo":20179, "v":253, "tot":4230, "per":"5.98", "ser":"HPM180PA01006615"}, {"cc":4398, "bo":20180, "v":370, "tot":4230, "per":"8.74", "ser":"HPM180PA01006615"}, {"cc":4398, "bo":20181, "v":153, "tot":4230, "per":"3.61", "ser":"HPM180PA01006615"}, {"cc":4398, "bo":20182, "v":148, "tot":4230, "per":"3.49", "ser":"HPM180PA01006615"}, {"cc":4398, "bo":20183, "v":244, "tot":4230, "per":"5.76", "ser":"HPM180PA01006615"}, {"cc":4398, "bo":20184, "v":37, "tot":4230, "per":"0.87", "ser":"HPM180PA01006615"}, {"cc":4398, "bo":20185, "v":306, "tot":4230, "per":"7.23", "ser":"HPM180PA01006615"}, {"cc":4398, "bo":20186, "v":172, "tot":4230, "per":"4.06", "ser":"HPM180PA01006615"}, {"cc":4398, "bo":20187, "v":113, "tot":4230, "per":"2.67", "ser":"HPM180PA01006615"}, {"cc":4398, "bo":20188, "v":35, "tot":4230, "per":"0.82", "ser":"HPM180PA01006615"}, {"cc":4398, "bo":20189, "v":154, "tot":4230, "per":"3.64", "ser":"HPM180PA01006615"}, {"cc":4398, "bo":20190, "v":88, "tot":4230, "per":"2.08", "ser":"HPM180PA01006615"}, {"cc":4398, "bo":20191, "v":84, "tot":4230, "per":"1.98", "ser":"HPM180PA01006615"}, {"cc":4398, "bo":20192, "v":250, "tot":4230, "per":"5.91", "ser":"HPM180PA01006615"}, {"cc":4398, "bo":20193, "v":309, "tot":4230, "per":"7.30", "ser":"HPM180PA01006615"}, {"cc":4398, "bo":20194, "v":46, "tot":4230, "per":"1.08", "ser":"HPM180PA01006615"}, {"cc":4398, "bo":20195, "v":243, "tot":4230, "per":"5.74", "ser":"HPM180PA01006615"}, {"cc":4398, "bo":20196, "v":117, "tot":4230, "per":"2.76", "ser":"HPM180PA01006615"}, {"cc":4398, "bo":20197, "v":316, "tot":4230, "per":"7.47", "ser":"HPM180PA01006615"}, {"cc":4398, "bo":20198, "v":22, "tot":4230, "per":"0.52", "ser":"HPM180PA01006615"}, {"cc":4398, "bo":20199, "v":154, "tot":4230, "per":"3.64", "ser":"HPM180PA01006615"}, {"cc":4398, "bo":20200, "v":341, "tot":4230, "per":"8.06", "ser":"HPM180PA01006615"}, {"cc":4398, "bo":20201, "v":225, "tot":4230, "per":"5.31", "ser":"HPM180PA01006615"}, {"cc":5567, "bo":43581, "v":7, "tot":280, "per":"2.50", "ser":"HPM180PA01006615"}, {"cc":5567, "bo":43582, "v":1, "tot":280, "per":"0.35", "ser":"HPM180PA01006615"}, {"cc":5567, "bo":43583, "v":5, "tot":280, "per":"1.78", "ser":"HPM180PA01006615"}, {"cc":5567, "bo":43584, "v":2, "tot":280, "per":"0.71", "ser":"HPM180PA01006615"}, {"cc":5567, "bo":43585, "v":2, "tot":280, "per":"0.71", "ser":"HPM180PA01006615"}, {"cc":5567, "bo":43586, "v":0, "tot":280, "per":"0.00", "ser":"HPM180PA01006615"}, {"cc":5567, "bo":43587, "v":0, "tot":280, "per":"0.00", "ser":"HPM180PA01006615"}, {"cc":5567, "bo":43588, "v":0, "tot":280, "per":"0.00", "ser":"HPM180PA01006615"}, {"cc":5567, "bo":43589, "v":1, "tot":280, "per":"0.35", "ser":"HPM180PA01006615"}, {"cc":5567, "bo":43590, "v":3, "tot":280, "per":"1.07", "ser":"HPM180PA01006615"}, {"cc":5567, "bo":43591, "v":1, "tot":280, "per":"0.35", "ser":"HPM180PA01006615"}, {"cc":5567, "bo":43592, "v":4, "tot":280, "per":"1.42", "ser":"HPM180PA01006615"}, {"cc":5567, "bo":43593, "v":1, "tot":280, "per":"0.35", "ser":"HPM180PA01006615"}, {"cc":5567, "bo":43594, "v":5, "tot":280, "per":"1.78", "ser":"HPM180PA01006615"}, {"cc":5567, "bo":43595, "v":3, "tot":280, "per":"1.07", "ser":"HPM180PA01006615"}, {"cc":5567, "bo":43596, "v":0, "tot":280, "per":"0.00", "ser":"HPM180PA01006615"}, {"cc":5567, "bo":43597, "v":0, "tot":280, "per":"0.00", "ser":"HPM180PA01006615"}, {"cc":5567, "bo":43598, "v":1, "tot":280, "per":"0.35", "ser":"HPM180PA01006615"}, {"cc":5567, "bo":43599, "v":0, "tot":280, "per":"0.00", "ser":"HPM180PA01006615"}, {"cc":5567, "bo":43600, "v":24, "tot":280, "per":"8.57", "ser":"HPM180PA01006615"}, {"cc":5567, "bo":43601, "v":0, "tot":280, "per":"0.00", "ser":"HPM180PA01006615"}, {"cc":5567, "bo":43602, "v":4, "tot":280, "per":"1.42", "ser":"HPM180PA01006615"}, {"cc":5567, "bo":43603, "v":3, "tot":280, "per":"1.07", "ser":"HPM180PA01006615"}, {"cc":5567, "bo":43604, "v":0, "tot":280, "per":"0.00", "ser":"HPM180PA01006615"}, {"cc":5567, "bo":43605, "v":0, "tot":280, "per":"0.00", "ser":"HPM180PA01006615"}, {"cc":5567, "bo":43606, "v":1, "tot":280, "per":"0.35", "ser":"HPM180PA01006615"}, {"cc":5567, "bo":43607, "v":3, "tot":280, "per":"1.07", "ser":"HPM180PA01006615"}, {"cc":5567, "bo":43608, "v":0, "tot":280, "per":"0.00", "ser":"HPM180PA01006615"}, {"cc":5567, "bo":43609, "v":1, "tot":280, "per":"0.35", "ser":"HPM180PA01006615"}, {"cc":5567, "bo":43610, "v":1, "tot":280, "per":"0.35", "ser":"HPM180PA01006615"}, {"cc":5567, "bo":43611, "v":0, "tot":280, "per":"0.00", "ser":"HPM180PA01006615"}, {"cc":5567, "bo":43612, "v":3, "tot":280, "per":"1.07", "ser":"HPM180PA01006615"}, {"cc":5567, "bo":43613, "v":0, "tot":280, "per":"0.00", "ser":"HPM180PA01006615"}, {"cc":5567, "bo":43614, "v":0, "tot":280, "per":"0.00", "ser":"HPM180PA01006615"}, {"cc":5567, "bo":43615, "v":1, "tot":280, "per":"0.35", "ser":"HPM180PA01006615"}, {"cc":5567, "bo":43616, "v":1, "tot":280, "per":"0.35", "ser":"HPM180PA01006615"}, {"cc":5567, "bo":43617, "v":0, "tot":280, "per":"0.00", "ser":"HPM180PA01006615"}, {"cc":5567, "bo":43618, "v":0, "tot":280, "per":"0.00", "ser":"HPM180PA01006615"}, {"cc":5567, "bo":43619, "v":0, "tot":280, "per":"0.00", "ser":"HPM180PA01006615"}, {"cc":5567, "bo":43620, "v":0, "tot":280, "per":"0.00", "ser":"HPM180PA01006615"}, {"cc":5567, "bo":43621, "v":1, "tot":280, "per":"0.35", "ser":"HPM180PA01006615"}, {"cc":5567, "bo":43622, "v":2, "tot":280, "per":"0.71", "ser":"HPM180PA01006615"}, {"cc":5567, "bo":43623, "v":0, "tot":280, "per":"0.00", "ser":"HPM180PA01006615"}, {"cc":5567, "bo":43624, "v":4, "tot":280, "per":"1.42", "ser":"HPM180PA01006615"}, {"cc":5567, "bo":43625, "v":0, "tot":280, "per":"0.00", "ser":"HPM180PA01006615"}, {"cc":5567, "bo":43626, "v":1, "tot":280, "per":"0.35", "ser":"HPM180PA01006615"}, {"cc":5567, "bo":43627, "v":0, "tot":280, "per":"0.00", "ser":"HPM180PA01006615"}, {"cc":5567, "bo":43628, "v":0, "tot":280, "per":"0.00", "ser":"HPM180PA01006615"}, {"cc":5567, "bo":43629, "v":0, "tot":280, "per":"0.00", "ser":"HPM180PA01006615"}, {"cc":5567, "bo":43630, "v":0, "tot":280, "per":"0.00", "ser":"HPM180PA01006615"}, {"cc":5567, "bo":43631, "v":1, "tot":280, "per":"0.35", "ser":"HPM180PA01006615"}, {"cc":5567, "bo":43632, "v":2, "tot":280, "per":"0.71", "ser":"HPM180PA01006615"}, {"cc":5567, "bo":43633, "v":0, "tot":280, "per":"0.00", "ser":"HPM180PA01006615"}, {"cc":5567, "bo":43634, "v":0, "tot":280, "per":"0.00", "ser":"HPM180PA01006615"}, {"cc":5567, "bo":43635, "v":0, "tot":280, "per":"0.00", "ser":"HPM180PA01006615"}, {"cc":5567, "bo":43636, "v":0, "tot":280, "per":"0.00", "ser":"HPM180PA01006615"}, {"cc":5567, "bo":43637, "v":0, "tot":280, "per":"0.00", "ser":"HPM180PA01006615"}, {"cc":5567, "bo":43638, "v":0, "tot":280, "per":"0.00", "ser":"HPM180PA01006615"}, {"cc":5567, "bo":43639, "v":1, "tot":280, "per":"0.35", "ser":"HPM180PA01006615"}, {"cc":5567, "bo":43640, "v":22, "tot":280, "per":"7.85", "ser":"HPM180PA01006615"}, {"cc":5567, "bo":43641, "v":1, "tot":280, "per":"0.35", "ser":"HPM180PA01006615"}, {"cc":5567, "bo":43642, "v":5, "tot":280, "per":"1.78", "ser":"HPM180PA01006615"}, {"cc":5567, "bo":43643, "v":0, "tot":280, "per":"0.00", "ser":"HPM180PA01006615"}, {"cc":5567, "bo":43644, "v":0, "tot":280, "per":"0.00", "ser":"HPM180PA01006615"}, {"cc":5567, "bo":43645, "v":2, "tot":280, "per":"0.71", "ser":"HPM180PA01006615"}, {"cc":5567, "bo":43646, "v":0, "tot":280, "per":"0.00", "ser":"HPM180PA01006615"}, {"cc":5567, "bo":43647, "v":0, "tot":280, "per":"0.00", "ser":"HPM180PA01006615"}, {"cc":5567, "bo":43648, "v":4, "tot":280, "per":"1.42", "ser":"HPM180PA01006615"}, {"cc":5567, "bo":43649, "v":1, "tot":280, "per":"0.35", "ser":"HPM180PA01006615"}, {"cc":5567, "bo":43650, "v":0, "tot":280, "per":"0.00", "ser":"HPM180PA01006615"}, {"cc":5567, "bo":43651, "v":1, "tot":280, "per":"0.35", "ser":"HPM180PA01006615"}, {"cc":5567, "bo":43652, "v":0, "tot":280, "per":"0.00", "ser":"HPM180PA01006615"}, {"cc":5567, "bo":43653, "v":0, "tot":280, "per":"0.00", "ser":"HPM180PA01006615"}, {"cc":5567, "bo":43654, "v":0, "tot":280, "per":"0.00", "ser":"HPM180PA01006615"}, {"cc":5567, "bo":43655, "v":0, "tot":280, "per":"0.00", "ser":"HPM180PA01006615"}, {"cc":5567, "bo":43656, "v":0, "tot":280, "per":"0.00", "ser":"HPM180PA01006615"}, {"cc":5567, "bo":43657, "v":3, "tot":280, "per":"1.07", "ser":"HPM180PA01006615"}, {"cc":5567, "bo":43658, "v":31, "tot":280, "per":"11.07", "ser":"HPM180PA01006615"}, {"cc":5567, "bo":43659, "v":3, "tot":280, "per":"1.07", "ser":"HPM180PA01006615"}, {"cc":5567, "bo":43660, "v":0, "tot":280, "per":"0.00", "ser":"HPM180PA01006615"}, {"cc":5567, "bo":43661, "v":0, "tot":280, "per":"0.00", "ser":"HPM180PA01006615"}, {"cc":5567, "bo":43662, "v":0, "tot":280, "per":"0.00", "ser":"HPM180PA01006615"}, {"cc":5567, "bo":43663, "v":1, "tot":280, "per":"0.35", "ser":"HPM180PA01006615"}, {"cc":5567, "bo":43664, "v":0, "tot":280, "per":"0.00", "ser":"HPM180PA01006615"}, {"cc":5567, "bo":43665, "v":0, "tot":280, "per":"0.00", "ser":"HPM180PA01006615"}, {"cc":5567, "bo":43666, "v":0, "tot":280, "per":"0.00", "ser":"HPM180PA01006615"}, {"cc":5567, "bo":43667, "v":0, "tot":280, "per":"0.00", "ser":"HPM180PA01006615"}, {"cc":5567, "bo":43668, "v":0, "tot":280, "per":"0.00", "ser":"HPM180PA01006615"}, {"cc":5567, "bo":43669, "v":0, "tot":280, "per":"0.00", "ser":"HPM180PA01006615"}, {"cc":5567, "bo":43670, "v":0, "tot":280, "per":"0.00", "ser":"HPM180PA01006615"}, {"cc":5567, "bo":43671, "v":0, "tot":280, "per":"0.00", "ser":"HPM180PA01006615"}, {"cc":5567, "bo":43672, "v":7, "tot":280, "per":"2.50", "ser":"HPM180PA01006615"}, {"cc":5567, "bo":43673, "v":0, "tot":280, "per":"0.00", "ser":"HPM180PA01006615"}, {"cc":5567, "bo":43674, "v":0, "tot":280, "per":"0.00", "ser":"HPM180PA01006615"}, {"cc":5567, "bo":43675, "v":0, "tot":280, "per":"0.00", "ser":"HPM180PA01006615"}, {"cc":5567, "bo":43676, "v":4, "tot":280, "per":"1.42", "ser":"HPM180PA01006615"}, {"cc":5567, "bo":43677, "v":8, "tot":280, "per":"2.85", "ser":"HPM180PA01006615"}, {"cc":5567, "bo":43678, "v":0, "tot":280, "per":"0.00", "ser":"HPM180PA01006615"}, {"cc":5567, "bo":43679, "v":0, "tot":280, "per":"0.00", "ser":"HPM180PA01006615"}, {"cc":5567, "bo":43680, "v":0, "tot":280, "per":"0.00", "ser":"HPM180PA01006615"}, {"cc":5567, "bo":43681, "v":2, "tot":280, "per":"0.71", "ser":"HPM180PA01006615"}, {"cc":5567, "bo":43682, "v":1, "tot":280, "per":"0.35", "ser":"HPM180PA01006615"}, {"cc":5567, "bo":43683, "v":0, "tot":280, "per":"0.00", "ser":"HPM180PA01006615"}, {"cc":5567, "bo":43684, "v":0, "tot":280, "per":"0.00", "ser":"HPM180PA01006615"}, {"cc":5567, "bo":43685, "v":0, "tot":280, "per":"0.00", "ser":"HPM180PA01006615"}, {"cc":5567, "bo":43686, "v":0, "tot":280, "per":"0.00", "ser":"HPM180PA01006615"}, {"cc":5567, "bo":43687, "v":22, "tot":280, "per":"7.85", "ser":"HPM180PA01006615"}, {"cc":5567, "bo":43688, "v":0, "tot":280, "per":"0.00", "ser":"HPM180PA01006615"}, {"cc":5567, "bo":43689, "v":0, "tot":280, "per":"0.00", "ser":"HPM180PA01006615"}, {"cc":5567, "bo":43690, "v":3, "tot":280, "per":"1.07", "ser":"HPM180PA01006615"}, {"cc":5567, "bo":43691, "v":5, "tot":280, "per":"1.78", "ser":"HPM180PA01006615"}, {"cc":5567, "bo":43692, "v":0, "tot":280, "per":"0.00", "ser":"HPM180PA01006615"}, {"cc":5567, "bo":43693, "v":3, "tot":280, "per":"1.07", "ser":"HPM180PA01006615"}, {"cc":5567, "bo":43694, "v":39, "tot":280, "per":"13.92", "ser":"HPM180PA01006615"}, {"cc":5567, "bo":43695, "v":0, "tot":280, "per":"0.00", "ser":"HPM180PA01006615"}, {"cc":5567, "bo":43696, "v":2, "tot":280, "per":"0.71", "ser":"HPM180PA01006615"}, {"cc":5567, "bo":43697, "v":0, "tot":280, "per":"0.00", "ser":"HPM180PA01006615"}, {"cc":5567, "bo":43698, "v":0, "tot":280, "per":"0.00", "ser":"HPM180PA01006615"}, {"cc":5567, "bo":43699, "v":12, "tot":280, "per":"4.28", "ser":"HPM180PA01006615"}, {"cc":5567, "bo":43700, "v":0, "tot":280, "per":"0.00", "ser":"HPM180PA01006615"}, {"cc":5567, "bo":43701, "v":0, "tot":280, "per":"0.00", "ser":"HPM180PA01006615"}, {"cc":5567, "bo":43702, "v":0, "tot":280, "per":"0.00", "ser":"HPM180PA01006615"}, {"cc":5567, "bo":43703, "v":0, "tot":280, "per":"0.00", "ser":"HPM180PA01006615"}, {"cc":5567, "bo":43704, "v":0, "tot":280, "per":"0.00", "ser":"HPM180PA01006615"}, {"cc":5567, "bo":43705, "v":0, "tot":280, "per":"0.00", "ser":"HPM180PA01006615"}, {"cc":5567, "bo":43706, "v":0, "tot":280, "per":"0.00", "ser":"HPM180PA01006615"}, {"cc":5567, "bo":43707, "v":2, "tot":280, "per":"0.71", "ser":"HPM180PA01006615"}, {"cc":5567, "bo":43708, "v":0, "tot":280, "per":"0.00", "ser":"HPM180PA01006615"}, {"cc":5567, "bo":43709, "v":0, "tot":280, "per":"0.00", "ser":"HPM180PA01006615"}, {"cc":5567, "bo":43710, "v":2, "tot":280, "per":"0.71", "ser":"HPM180PA01006615"}, {"cc":5567, "bo":43711, "v":1, "tot":280, "per":"0.35", "ser":"HPM180PA01006615"}, {"cc":5567, "bo":43712, "v":1, "tot":280, "per":"0.35", "ser":"HPM180PA01006615"}, {"cc":5567, "bo":43713, "v":0, "tot":280, "per":"0.00", "ser":"HPM180PA01006615"}, {"cc":5567, "bo":43714, "v":2, "tot":280, "per":"0.71", "ser":"HPM180PA01006615"}], "cos":[{"cc":1, "cn":"blank", "ct":54}, {"cc":1, "cn":"blank-ballots", "ct":2}, {"cc":1, "cn":"expected-voters", "ct":888}, {"cc":1, "cn":"misfeed-ballots", "ct":2}, {"cc":1, "cn":"number-of-voters-who-actually-voted", "ct":685}, {"cc":1, "cn":"overvote-ballots", "ct":69}, {"cc":1, "cn":"overvote-count", "ct":23}, {"cc":1, "cn":"overvotes", "ct":48}, {"cc":1, "cn":"processed-ballots", "ct":685}, {"cc":1, "cn":"processed-count", "ct":685}, {"cc":1, "cn":"resets", "ct":2}, {"cc":1, "cn":"returned-ballots", "ct":2}, {"cc":1, "cn":"turn-out", "ct":77.13}, {"cc":1, "cn":"under-votes", "ct":2588}, {"cc":1, "cn":"undervote-ballots", "ct":603}, {"cc":1, "cn":"undervote-count", "ct":405}, {"cc":1, "cn":"undervotes", "ct":2612}, {"cc":1, "cn":"valid-ballot-rate", "ct":100}, {"cc":1, "cn":"valid-votes", "ct":8220}, {"cc":1, "cn":"votes-obtained-by-all-candidates", "ct":5332}, {"cc":26, "cn":"blank", "ct":275}, {"cc":26, "cn":"blank-ballots", "ct":2}, {"cc":26, "cn":"expected-voters", "ct":888}, {"cc":26, "cn":"misfeed-ballots", "ct":2}, {"cc":26, "cn":"number-of-voters-who-actually-voted", "ct":685}, {"cc":26, "cn":"overvote-ballots", "ct":69}, {"cc":26, "cn":"overvote-count", "ct":0}, {"cc":26, "cn":"overvotes", "ct":0}, {"cc":26, "cn":"processed-ballots", "ct":685}, {"cc":26, "cn":"processed-count", "ct":685}, {"cc":26, "cn":"resets", "ct":2}, {"cc":26, "cn":"returned-ballots", "ct":2}, {"cc":26, "cn":"turn-out", "ct":77.13}, {"cc":26, "cn":"under-votes", "ct":273}, {"cc":26, "cn":"undervote-ballots", "ct":603}, {"cc":26, "cn":"undervote-count", "ct":275}, {"cc":26, "cn":"undervotes", "ct":275}, {"cc":26, "cn":"valid-ballot-rate", "ct":100}, {"cc":26, "cn":"valid-votes", "ct":685}, {"cc":26, "cn":"votes-obtained-by-all-candidates", "ct":410}, {"cc":107, "cn":"blank", "ct":240}, {"cc":107, "cn":"blank-ballots", "ct":2}, {"cc":107, "cn":"expected-voters", "ct":888}, {"cc":107, "cn":"misfeed-ballots", "ct":2}, {"cc":107, "cn":"number-of-voters-who-actually-voted", "ct":685}, {"cc":107, "cn":"overvote-ballots", "ct":69}, {"cc":107, "cn":"overvote-count", "ct":0}, {"cc":107, "cn":"overvotes", "ct":0}, {"cc":107, "cn":"processed-ballots", "ct":685}, {"cc":107, "cn":"processed-count", "ct":685}, {"cc":107, "cn":"resets", "ct":2}, {"cc":107, "cn":"returned-ballots", "ct":2}, {"cc":107, "cn":"turn-out", "ct":77.13}, {"cc":107, "cn":"under-votes", "ct":238}, {"cc":107, "cn":"undervote-ballots", "ct":603}, {"cc":107, "cn":"undervote-count", "ct":240}, {"cc":107, "cn":"undervotes", "ct":240}, {"cc":107, "cn":"valid-ballot-rate", "ct":100}, {"cc":107, "cn":"valid-votes", "ct":685}, {"cc":107, "cn":"votes-obtained-by-all-candidates", "ct":445}, {"cc":238, "cn":"blank", "ct":99}, {"cc":238, "cn":"blank-ballots", "ct":2}, {"cc":238, "cn":"expected-voters", "ct":888}, {"cc":238, "cn":"misfeed-ballots", "ct":2}, {"cc":238, "cn":"number-of-voters-who-actually-voted", "ct":685}, {"cc":238, "cn":"overvote-ballots", "ct":69}, {"cc":238, "cn":"overvote-count", "ct":10}, {"cc":238, "cn":"overvotes", "ct":16}, {"cc":238, "cn":"processed-ballots", "ct":685}, {"cc":238, "cn":"processed-count", "ct":685}, {"cc":238, "cn":"resets", "ct":2}, {"cc":238, "cn":"returned-ballots", "ct":2}, {"cc":238, "cn":"turn-out", "ct":77.13}, {"cc":238, "cn":"under-votes", "ct":1437}, {"cc":238, "cn":"undervote-ballots", "ct":603}, {"cc":238, "cn":"undervote-count", "ct":455}, {"cc":238, "cn":"undervotes", "ct":1447}, {"cc":238, "cn":"valid-ballot-rate", "ct":100}, {"cc":238, "cn":"valid-votes", "ct":3425}, {"cc":238, "cn":"votes-obtained-by-all-candidates", "ct":1928}, {"cc":459, "cn":"blank", "ct":221}, {"cc":459, "cn":"blank-ballots", "ct":2}, {"cc":459, "cn":"expected-voters", "ct":888}, {"cc":459, "cn":"misfeed-ballots", "ct":2}, {"cc":459, "cn":"number-of-voters-who-actually-voted", "ct":685}, {"cc":459, "cn":"overvote-ballots", "ct":69}, {"cc":459, "cn":"overvote-count", "ct":0}, {"cc":459, "cn":"overvotes", "ct":0}, {"cc":459, "cn":"processed-ballots", "ct":685}, {"cc":459, "cn":"processed-count", "ct":685}, {"cc":459, "cn":"resets", "ct":2}, {"cc":459, "cn":"returned-ballots", "ct":2}, {"cc":459, "cn":"turn-out", "ct":77.13}, {"cc":459, "cn":"under-votes", "ct":219}, {"cc":459, "cn":"undervote-ballots", "ct":603}, {"cc":459, "cn":"undervote-count", "ct":221}, {"cc":459, "cn":"undervotes", "ct":221}, {"cc":459, "cn":"valid-ballot-rate", "ct":100}, {"cc":459, "cn":"valid-votes", "ct":685}, {"cc":459, "cn":"votes-obtained-by-all-candidates", "ct":464}, {"cc":1124, "cn":"blank", "ct":26}, {"cc":1124, "cn":"blank-ballots", "ct":2}, {"cc":1124, "cn":"expected-voters", "ct":888}, {"cc":1124, "cn":"misfeed-ballots", "ct":2}, {"cc":1124, "cn":"number-of-voters-who-actually-voted", "ct":685}, {"cc":1124, "cn":"overvote-ballots", "ct":69}, {"cc":1124, "cn":"overvote-count", "ct":2}, {"cc":1124, "cn":"overvotes", "ct":2}, {"cc":1124, "cn":"processed-ballots", "ct":685}, {"cc":1124, "cn":"processed-count", "ct":685}, {"cc":1124, "cn":"resets", "ct":2}, {"cc":1124, "cn":"returned-ballots", "ct":2}, {"cc":1124, "cn":"turn-out", "ct":77.13}, {"cc":1124, "cn":"under-votes", "ct":24}, {"cc":1124, "cn":"undervote-ballots", "ct":603}, {"cc":1124, "cn":"undervote-count", "ct":26}, {"cc":1124, "cn":"undervotes", "ct":26}, {"cc":1124, "cn":"valid-ballot-rate", "ct":100}, {"cc":1124, "cn":"valid-votes", "ct":685}, {"cc":1124, "cn":"votes-obtained-by-all-candidates", "ct":657}, {"cc":2758, "cn":"blank", "ct":47}, {"cc":2758, "cn":"blank-ballots", "ct":2}, {"cc":2758, "cn":"expected-voters", "ct":888}, {"cc":2758, "cn":"misfeed-ballots", "ct":2}, {"cc":2758, "cn":"number-of-voters-who-actually-voted", "ct":685}, {"cc":2758, "cn":"overvote-ballots", "ct":69}, {"cc":2758, "cn":"overvote-count", "ct":2}, {"cc":2758, "cn":"overvotes", "ct":2}, {"cc":2758, "cn":"processed-ballots", "ct":685}, {"cc":2758, "cn":"processed-count", "ct":685}, {"cc":2758, "cn":"resets", "ct":2}, {"cc":2758, "cn":"returned-ballots", "ct":2}, {"cc":2758, "cn":"turn-out", "ct":77.13}, {"cc":2758, "cn":"under-votes", "ct":45}, {"cc":2758, "cn":"undervote-ballots", "ct":603}, {"cc":2758, "cn":"undervote-count", "ct":47}, {"cc":2758, "cn":"undervotes", "ct":47}, {"cc":2758, "cn":"valid-ballot-rate", "ct":100}, {"cc":2758, "cn":"valid-votes", "ct":685}, {"cc":2758, "cn":"votes-obtained-by-all-candidates", "ct":636}, {"cc":4398, "cn":"blank", "ct":23}, {"cc":4398, "cn":"blank-ballots", "ct":2}, {"cc":4398, "cn":"expected-voters", "ct":888}, {"cc":4398, "cn":"misfeed-ballots", "ct":2}, {"cc":4398, "cn":"number-of-voters-who-actually-voted", "ct":685}, {"cc":4398, "cn":"overvote-ballots", "ct":69}, {"cc":4398, "cn":"overvote-count", "ct":22}, {"cc":4398, "cn":"overvotes", "ct":39}, {"cc":4398, "cn":"processed-ballots", "ct":685}, {"cc":4398, "cn":"processed-count", "ct":685}, {"cc":4398, "cn":"resets", "ct":2}, {"cc":4398, "cn":"returned-ballots", "ct":2}, {"cc":4398, "cn":"turn-out", "ct":77.13}, {"cc":4398, "cn":"under-votes", "ct":2380}, {"cc":4398, "cn":"undervote-ballots", "ct":603}, {"cc":4398, "cn":"undervote-count", "ct":450}, {"cc":4398, "cn":"undervotes", "ct":2400}, {"cc":4398, "cn":"valid-ballot-rate", "ct":100}, {"cc":4398, "cn":"valid-votes", "ct":6850}, {"cc":4398, "cn":"votes-obtained-by-all-candidates", "ct":4230}, {"cc":5567, "cn":"blank", "ct":381}, {"cc":5567, "cn":"blank-ballots", "ct":2}, {"cc":5567, "cn":"expected-voters", "ct":888}, {"cc":5567, "cn":"misfeed-ballots", "ct":2}, {"cc":5567, "cn":"number-of-voters-who-actually-voted", "ct":685}, {"cc":5567, "cn":"overvote-ballots", "ct":69}, {"cc":5567, "cn":"overvote-count", "ct":24}, {"cc":5567, "cn":"overvotes", "ct":87}, {"cc":5567, "cn":"processed-ballots", "ct":685}, {"cc":5567, "cn":"processed-count", "ct":685}, {"cc":5567, "cn":"resets", "ct":2}, {"cc":5567, "cn":"returned-ballots", "ct":2}, {"cc":5567, "cn":"turn-out", "ct":77.13}, {"cc":5567, "cn":"under-votes", "ct":379}, {"cc":5567, "cn":"undervote-ballots", "ct":603}, {"cc":5567, "cn":"undervote-count", "ct":381}, {"cc":5567, "cn":"undervotes", "ct":381}, {"cc":5567, "cn":"valid-ballot-rate", "ct":100}, {"cc":5567, "cn":"valid-votes", "ct":685}, {"cc":5567, "cn":"votes-obtained-by-all-candidates", "ct":280}], "sts":{"expected":9, "received":9, "per":"100.00"}, "obs":[]}