{"rc":18947, "rcc":"3126025", "rn":"SOTERO NUESA", "can":"Barangay", "cll":true, "cl":5, "url":"18/18947", "srs":{}, "tcs":[], "cs":[1, 113, 4561, 5567, 32, 2921, 1287, 476, 256], "pps":[{"ppc":32893, "ppcc":"31260029", "ppn":"NUESA ELEMENTARY SCHOOL", "vbs":[{"vbc":32893, "pre":"31260029", "cpre":"0086A, 0086B, 0088A, 0088B", "url":"32/32893", "type":"AUTOMATED", "cs":[1, 32, 113, 256, 476, 1287, 2921, 4561, 5567]}]}, {"ppc":32894, "ppcc":"31260030", "ppn":"NUESA ELEMENTARY SCHOOL", "vbs":[{"vbc":32894, "pre":"31260030", "cpre":"0087A, 0087B, 0094A, 0095A, 0095B", "url":"32/32894", "type":"AUTOMATED", "cs":[1, 32, 113, 256, 476, 1287, 2921, 4561, 5567]}]}, {"ppc":32895, "ppcc":"31260031", "ppn":"NUESA ELEMENTARY SCHOOL", "vbs":[{"vbc":32895, "pre":"31260031", "cpre":"0089A, 0089B, 0091A, 0091B, 0093A", "url":"32/32895", "type":"AUTOMATED", "cs":[1, 32, 113, 256, 476, 1287, 2921, 4561, 5567]}]}, {"ppc":32896, "ppcc":"31260032", "ppn":"NUESA ELEMENTARY SCHOOL", "vbs":[{"vbc":32896, "pre":"31260032", "cpre":"0090A, 0090B, 0092A, 0096A, 0096B", "url":"32/32896", "type":"AUTOMATED", "cs":[1, 32, 113, 256, 476, 1287, 2921, 4561, 5567]}]}], "total-vb":4, "total-voters":3280}